{"2inW4PFfZmoE6ldqn2wTAQ==":"logo%20(branco)-198x127.png","08SAXkH6K4xcLitzgIqyPA==":"mbr-1920x980.jpg","2gk0fCxbgFu4/zrq1hw7Mg==":"black-football-soccer-backgrounds-powerpoint-1600x1000.jpg","nK88pG68pMTW7iddekDd4Q==":"black-football-soccer-backgrounds-powerpoint-1-1600x1000.jpg","3+AeLTHeXSd1zm+ZCPnRtg==":"black-football-soccer-backgrounds-powerpoint-2-1600x1000.jpg","diffE/95dgA33vhU8Xb6lw==":"mbr-1620x1080.jpg","G+ORmBpQ3QPO3kRUN2XG5A==":"logo%20(branco)-192x123.png","4+DzqXFpj/z2AIwVP9lcYQ==":"background5.jpg","LiUIORYxGXGMpCM1i0NnEA==":"06.jpg","Ly+mdm63lVz6CqSX2vcU6g==":"background3.jpg","ihlkf69UyfSmhSyJ1Jvc6w==":"jumbotron.jpg","eoYU/aiNC4Ce+rsKshUaWw==":"jumbotron2.jpg","p0KyD8tweiX6hpLVeU699w==":"01%20-%20fineo%20ara%C3%9Ajo%20(zhuhai%20futsal%20e%20sele%C3%A7%C3%A3o%20azeri)-1079x649.jpg","hD+A90Qmhn5DEVNMKxMxTQ==":"01%20-%20fineo%20ara%C3%9Ajo%20(zhuhai%20futsal%20e%20sele%C3%A7%C3%A3o%20azeri)-1079x649.jpg","r34loWxeuxMJPYVwXmqfbg==":"black-football-soccer-backgrounds-powerpoint-3-1600x1000.jpg","r0M9jpuaxOMU9SmNWvdd4g==":"black-football-soccer-backgrounds-powerpoint-4-1600x1000.jpg","x7EuIKL11SU1OvRfleL2ww==":"logo%20(branco)-96x62.png","jAFLyhMsjB2qi6Q6VmTQBg==":"01%20-%20fineo%20ara%C3%9Ajo%20(zhuhai%20futsal%20e%20sele%C3%A7%C3%A3o%20azeri)-1079x649.jpg","2pBSpqdCUhc4Ki8uSyBXGw==":"02%20-%20jezin%20(ae%20uruguaianense)-1079x649.jpg","sUbSMCyZcfbsPlDxowniWQ==":"03%20-%20johnny%20gomes%20(copagril%20futsal)-1079x649.jpg","aA33mu7qs55W7jspLRf68A==":"04%20-%20thiago%20bissoni%20(fp%20halle-gooik)-1079x649.jpg","H+QcIhtbSXnaSMzK+5pq5Q==":"05%20-%20j%C3%89%20(atl%C3%A2ntico%20erechim)-1079x649.jpg","3XtVpYjf6lcG8Y+Tgb0kpw==":"06%20-%20nen%C3%8A%20(atl%C3%A2ntico%20erechim)-1079x649.jpg","1eKdgivKDy0/h76jZXfgOg==":"07%20-%20halison%20(guarani%20futsal)-1079x649.jpg","J4YPPvHe4KoaZtaac3vVVw==":"#01-968x968.png","p2a1youdAPZJZ+X8E2OgLA==":"02-968x968.png","44yHf8eu1SKAt5UiYGbSHA==":"03-1080x1080.png","bebfh2I2Tfe91MZRyrQZeQ==":"04-968x968.png","ravdMqUvUvs2VoogjnXopQ==":"05-1080x1080.png","ugqbIT7HKfutn0J4ChFNgw==":"06-968x968.jpg","tI3BwazwStDILYhHfmQMJQ==":"07-1080x1080.png","z2tP4FNtEkwigtxt5USh/A==":"08-1080x1080.png","ftTAnBxRRTF6y5CTrZX8Gg==":"09-1080x1080.jpg","39Z5F49jTou8Kk38RAtpmw==":"10-1080x1080.png","Z55P+8yQSU9IF0QYNnMSLg==":"11-968x968.jpg","4STLopsWbCSjRk3iaGWVtw==":"12-1080x1080.jpg","pqtMz9mx29XRJ0e7gKbRGA==":"13-968x968.png","qG+hg2QKFUemZQ3yYpx1Sg==":"14-1080x1080.jpg","dIeNxtsweU7QiXksVTs8Ew==":"15-1080x1080.png","RKfhq2I+IevLDt97XD5jvg==":"16-968x968.png","ld1vPUR6YxR61BHefY/Sqw==":"01%20-%20fineo%20ara%C3%9Ajo%20(zhuhai%20futsal%20e%20sele%C3%A7%C3%A3o%20azeri)-400x241.jpg","VcjuhIpGa38ehKQs2moTQQ==":"01%20-%20fineo%20ara%C3%9Ajo%20(zhuhai%20futsal%20e%20sele%C3%A7%C3%A3o%20azeri)-400x241.jpg","3cm1xC4NWSgrEQlonBqkUg==":"01%20-%20fineo%20ara%C3%9Ajo%20(zhuhai%20futsal%20e%20sele%C3%A7%C3%A3o%20azeri)-300x180.jpg","dT0z9rJbh6ToLf3hM9ZVlw==":"01%20-%20fineo%20ara%C3%9Ajo%20(zhuhai%20futsal%20e%20sele%C3%A7%C3%A3o%20azeri)-300x180.jpg","TJr6EcAGYA5ikcL00vOdMw==":"02%20-%20jezin%20(ae%20uruguaianense)-300x180.jpg","iYQPEWmtRg6amM1s5OXYjQ==":"03%20-%20johnny%20gomes%20(copagril%20futsal)-300x180.jpg","1ozNO4ewlOwgtcawvpwnWw==":"04%20-%20thiago%20bissoni%20(fp%20halle-gooik)-300x180.jpg","sHxeHCINJ9tzltDiqpW+HA==":"background1.jpg","4ZcvT66nU8YkA+Fmi519xA==":"01%20-%20fineo%20ara%C3%9Ajo%20(zhuhai%20futsal%20e%20sele%C3%A7%C3%A3o%20azeri)-400x241.jpg","Os1hpkyKHdJTZJYYSjSiXg==":"01-1.jpg","Q8kyWdiPLYJ/4F1Ss+9IyA==":"03-3.jpg","HoeEF4HfT9nMa9Cg+v0y1w==":"02-2.jpg","D/MJwuutwIhlmcioKCvGqA==":"04-4.jpg","0SMmzj3G3c+tc1jddRaDMA==":"01%20-%20fineo%20ara%C3%9Ajo%20(zhuhai%20futsal%20e%20sele%C3%A7%C3%A3o%20azeri)-464x279.jpg","7jrkoRe2VHbQSHHpppaIyA==":"02%20-%20jezin%20(ae%20uruguaianense)-464x279.jpg","DT7E0aF2M2pDbqUVTK86Ug==":"03%20-%20johnny%20gomes%20(copagril%20futsal)-464x279.jpg","M5EHj80XNRJkuILF6jC95Q==":"04%20-%20thiago%20bissoni%20(fp%20halle-gooik)-464x279.jpg","3QyQ3OGrnOCpGKJiguT6HQ==":"05%20-%20j%C3%89%20(atl%C3%A2ntico%20erechim)-464x279.jpg","8SBYO7FNNymYT0CIzfTGxw==":"05%20-%20j%C3%89%20(atl%C3%A2ntico%20erechim)-300x180.jpg","mPWZLG9ztZEwN8vpZQjcvg==":"06%20-%20nen%C3%8A%20(atl%C3%A2ntico%20erechim)-300x180.jpg","SiiET6r2X9zVwG6S1k/DCg==":"07%20-%20halison%20(guarani%20futsal)-300x180.jpg","dfF/hUls9orVezKE1t/RKg==":"08%20-%20lucas%20alencar%20(ad%20indaiatuba)-300x180.jpg","3V4D4eXnBEHdy7niWWGLEQ==":"09%20-%20josiel%20dornelles%20(asif%20futsal)-300x180.jpg","959pZqdmrMew0UD/5hlE+g==":"10%20-%20eduard%20moura%20(umuarama%20futsal)-300x180.jpg","tLJfcr5QhcrW2JmY5INv9A==":"33927544_158416618346638_5415452481737981952_n-1080x1080.jpg","3mYNsRFKwj2EvwI63pEUeQ==":"nen%C3%AA%20(07.06)-1080x1080.jpg","2KhScDrY9y/S5KZeL4LsXg==":"backgroundhome-2000x1333.jpg","nxH6w4pkp4ShXxbGOWqZxQ==":"bgquemsomos-800x450.jpg","Wx4XQfWh6TBo2u4eQLzlxg==":"futsal1-1680x1050.jpg","ZsUkJosqAntvE2phd9bQbw==":"futsal1-1-1680x1050.jpg","iVd4FtTvPBbdAuNR1AyBEg==":"makanan-sehat-wajib-bagi-para-pemain-futsal-670x335.jpg","9PSZxEN+tw1PvCFkRZnwGg==":"3a0f1e5b98d2bd3d83161abef19a31ae_large3-2-1024x768.jpg","skPKJutaBUKHj0TU4SPN9A==":"futsal1-2-1680x1050.jpg","y/SmHCv1qilmh7AsZ/e9gA==":"futsal1-3-1680x1050.jpg","Z89hYeqRXJo6P1stKbMkUw==":"gabriel-1024x707.jpg","BsHHZfYpGApnzjKq885fcQ==":"gabriel-1-1024x707.jpg","vtS78gun157CInMW2Pz+CA==":"gabriel2-1024x575.png","yiCuTKwZHseVLcs96/pcDQ==":"gabriel2-1-1024x575.png","ocSuvWskJsqctpDilYvLMw==":"capagdl-2000x1333.jpg","32KE3ciwuozzzFUOFFVMow==":"capagdlsports-2000x1333.png","432EzRmHhfYwLiX2JGOBVw==":"backgroundhomefinal-1024x683.png","OtgrlaFe0NFDMblPzf9h8Q==":"fotogabriel-1024x575.png","3R4+Odrt2dY0Xbb7yrrVeQ==":"12%20-%20gustavo-300x180.jpg","jX10miLrG+CMuksbi6N+tA==":"12%20-%20gustavo-300x180.jpg","pDtJHzOn/+vXm2rZewvE6g==":"12%20-%20tiago%20selbach-300x180.jpg","mGtUc8XD9RDfhkvKWjz5gg==":"tiago%20s-300x180.jpg","JGbWVgdP5y0Hss0ICG2T1Q==":"gustavo%20c.-300x180.jpg","E9XRyS/jKajToIq7Msv6Ig==":"logo%20gdl%20sports%20-%20branco-330x239.png","kXiRxFNbPj7k8hdXdwWmVA==":"mbr-1920x1280.jpg","rCxV3nq4l24mLCFJlV6pBw==":"logo%20gdl%20sports%20-%20bs-318x269.png","cFzOaZucXQD8XUPRocFZ2Q==":"backgdlnovo-2000x901.jpg","8LuHtT058XWFtGhj4CLXgQ==":"backgdloutro-2000x901.jpg","0Ed0/pxXH2bS2QUJFgHiYg==":"backgdlgrande-2000x901.jpg","PaVPa/53jqi4I7hmcYC2sg==":"logo%20gdl%20sports-230x194.png"}